{
  "daily-quran": [
    {
      "day": 1,
      "sura": 1,
      "aya": "1,2,3,4,5,6,7"
    },
    {
      "day": 2,
      "sura": 2,
      "aya": "2,3,4,5"
    },
    {
      "day": 3,
      "sura": 2,
      "aya": "21,22"
    },
    {
      "day": 4,
      "sura": 2,
      "aya": "28,29"
    },
    {
      "day": 5,
      "sura": 2,
      "aya": 107
    },
    {
      "day": 6,
      "sura": 2,
      "aya": "115,116,117"
    },
    {
      "day": 7,
      "sura": 2,
      "aya": "127,128,129"
    },
    {
      "day": 8,
      "sura": 2,
      "aya": 136
    },
    {
      "day": 9,
      "sura": 2,
      "aya": 152
    },
    {
      "day": 10,
      "sura": 2,
      "aya": 153
    },
    {
      "day": 11,
      "sura": 2,
      "aya": "155,156,157"
    },
    {
      "day": 12,
      "sura": 2,
      "aya": "163,164,165"
    },
    {
      "day": 13,
      "sura": 2,
      "aya": 172
    },
    {
      "day": 14,
      "sura": 2,
      "aya": 183
    },
    {
      "day": 15,
      "sura": 2,
      "aya": 186
    },
    {
      "day": 16,
      "sura": 2,
      "aya": 190
    },
    {
      "day": 17,
      "sura": 2,
      "aya": 195
    },
    {
      "day": 18,
      "sura": 2,
      "aya": "200,201,202"
    },
    {
      "day": 19,
      "sura": 2,
      "aya": "208,209"
    },
    {
      "day": 20,
      "sura": 2,
      "aya": 254
    },
    {
      "day": 21,
      "sura": 2,
      "aya": 255
    },
    {
      "day": 22,
      "sura": 2,
      "aya": 256
    },
    {
      "day": 23,
      "sura": 2,
      "aya": "261,262,263"
    },
    {
      "day": 24,
      "sura": 2,
      "aya": 264
    },
    {
      "day": 25,
      "sura": 2,
      "aya": "284,285"
    },
    {
      "day": 26,
      "sura": 3,
      "aya": "5,6"
    },
    {
      "day": 27,
      "sura": 3,
      "aya": "8,9"
    },
    {
      "day": 28,
      "sura": 3,
      "aya": 14
    },
    {
      "day": 29,
      "sura": 3,
      "aya": "16,17"
    },
    {
      "day": 30,
      "sura": 3,
      "aya": 16
    },
    {
      "day": 31,
      "sura": 3,
      "aya": "26,27"
    },
    {
      "day": 32,
      "sura": 3,
      "aya": "29,30"
    },
    {
      "day": 33,
      "sura": 3,
      "aya": "31,32"
    },
    {
      "day": 34,
      "sura": 3,
      "aya": "36,37"
    },
    {
      "day": 35,
      "sura": 3,
      "aya": "42,43"
    },
    {
      "day": 36,
      "sura": 3,
      "aya": "45,46,47"
    },
    {
      "day": 37,
      "sura": 3,
      "aya": "48,49"
    },
    {
      "day": 38,
      "sura": 3,
      "aya": "50,51,52"
    },
    {
      "day": 39,
      "sura": 3,
      "aya": "58,59,60"
    },
    {
      "day": 40,
      "sura": 3,
      "aya": 84
    },
    {
      "day": 41,
      "sura": 3,
      "aya": 102
    },
    {
      "day": 42,
      "sura": 3,
      "aya": 129
    },
    {
      "day": 43,
      "sura": 3,
      "aya": "130,131,132,133,134,135,136"
    },
    {
      "day": 44,
      "sura": 3,
      "aya": "147,148"
    },
    {
      "day": 45,
      "sura": 3,
      "aya": "190,191"
    },
    {
      "day": 46,
      "sura": 3,
      "aya": "192,193,194,195"
    },
    {
      "day": 47,
      "sura": 4,
      "aya": 40
    },
    {
      "day": 48,
      "sura": 4,
      "aya": 58
    },
    {
      "day": 49,
      "sura": 4,
      "aya": "125,126"
    },
    {
      "day": 50,
      "sura": 4,
      "aya": "131,132"
    },
    {
      "day": 51,
      "sura": 4,
      "aya": 134
    },
    {
      "day": 52,
      "sura": 4,
      "aya": 135
    },
    {
      "day": 53,
      "sura": 4,
      "aya": "136,137"
    },
    {
      "day": 54,
      "sura": 4,
      "aya": "148,149"
    },
    {
      "day": 55,
      "sura": 4,
      "aya": "163,164,165"
    },
    {
      "day": 56,
      "sura": 4,
      "aya": 170
    },
    {
      "day": 57,
      "sura": 4,
      "aya": "172,173"
    },
    {
      "day": 58,
      "sura": 4,
      "aya": "174,175"
    },
    {
      "day": 59,
      "sura": 5,
      "aya": "8,9,10"
    },
    {
      "day": 60,
      "sura": 5,
      "aya": 35
    },
    {
      "day": 61,
      "sura": 5,
      "aya": "75,76"
    },
    {
      "day": 62,
      "sura": 6,
      "aya": "1,2,3"
    },
    {
      "day": 63,
      "sura": 5,
      "aya": "109,110"
    },
    {
      "day": 64,
      "sura": 5,
      "aya": "111,112,113,114,115"
    },
    {
      "day": 65,
      "sura": 5,
      "aya": "116,117,118,119,120"
    },
    {
      "day": 66,
      "sura": 6,
      "aya": "12,13"
    },
    {
      "day": 67,
      "sura": 6,
      "aya": 14
    },
    {
      "day": 68,
      "sura": 6,
      "aya": "17,18"
    },
    {
      "day": 69,
      "sura": 6,
      "aya": 38
    },
    {
      "day": 70,
      "sura": 6,
      "aya": 50
    },
    {
      "day": 71,
      "sura": 6,
      "aya": 51
    },
    {
      "day": 72,
      "sura": 6,
      "aya": 54
    },
    {
      "day": 73,
      "sura": 6,
      "aya": 59
    },
    {
      "day": 74,
      "sura": 6,
      "aya": 60
    },
    {
      "day": 75,
      "sura": 6,
      "aya": "61,62"
    },
    {
      "day": 76,
      "sura": 6,
      "aya": "63,64"
    },
    {
      "day": 77,
      "sura": 6,
      "aya": 73
    },
    {
      "day": 78,
      "sura": 6,
      "aya": "74,75"
    },
    {
      "day": 79,
      "sura": 6,
      "aya": 98
    },
    {
      "day": 80,
      "sura": 6,
      "aya": "76,77,78,79"
    },
    {
      "day": 81,
      "sura": 6,
      "aya": "95,96,97"
    },
    {
      "day": 82,
      "sura": 6,
      "aya": 99
    },
    {
      "day": 83,
      "sura": 6,
      "aya": "101,102,103"
    },
    {
      "day": 84,
      "sura": 6,
      "aya": 104
    },
    {
      "day": 85,
      "sura": 6,
      "aya": 117
    },
    {
      "day": 86,
      "sura": 6,
      "aya": 141
    },
    {
      "day": 87,
      "sura": 6,
      "aya": 151
    },
    {
      "day": 88,
      "sura": 6,
      "aya": 160
    },
    {
      "day": 89,
      "sura": 6,
      "aya": "162,163,164"
    },
    {
      "day": 90,
      "sura": 7,
      "aya": "8,9"
    },
    {
      "day": 91,
      "sura": 7,
      "aya": "10,11"
    },
    {
      "day": 92,
      "sura": 7,
      "aya": "23,24,25"
    },
    {
      "day": 93,
      "sura": 7,
      "aya": "35,36"
    },
    {
      "day": 94,
      "sura": 7,
      "aya": "31,32,33"
    },
    {
      "day": 95,
      "sura": 7,
      "aya": "42,43"
    },
    {
      "day": 96,
      "sura": 7,
      "aya": 54
    },
    {
      "day": 97,
      "sura": 7,
      "aya": "55,56"
    },
    {
      "day": 98,
      "sura": 7,
      "aya": 143
    },
    {
      "day": 99,
      "sura": 7,
      "aya": "59,65,73,85,103"
    },
    {
      "day": 100,
      "sura": 7,
      "aya": 158
    },
    {
      "day": 101,
      "sura": 7,
      "aya": 185
    },
    {
      "day": 102,
      "sura": 7,
      "aya": "205,206"
    },
    {
      "day": 103,
      "sura": 8,
      "aya": "2,3,4"
    },
    {
      "day": 104,
      "sura": 8,
      "aya": "28,29"
    },
    {
      "day": 105,
      "sura": 8,
      "aya": 53
    },
    {
      "day": 106,
      "sura": 9,
      "aya": 24
    },
    {
      "day": 107,
      "sura": 9,
      "aya": 51
    },
    {
      "day": 108,
      "sura": 9,
      "aya": "71,72"
    },
    {
      "day": 109,
      "sura": 9,
      "aya": 105
    },
    {
      "day": 110,
      "sura": 9,
      "aya": 119
    },
    {
      "day": 111,
      "sura": 10,
      "aya": "3,4"
    },
    {
      "day": 112,
      "sura": 10,
      "aya": "5,6"
    },
    {
      "day": 113,
      "sura": 10,
      "aya": "9,10"
    },
    {
      "day": 114,
      "sura": 10,
      "aya": 23
    },
    {
      "day": 115,
      "sura": 10,
      "aya": "25,26,27"
    },
    {
      "day": 116,
      "sura": 10,
      "aya": "31,32"
    },
    {
      "day": 117,
      "sura": 10,
      "aya": "34,35"
    },
    {
      "day": 118,
      "sura": 10,
      "aya": 41
    },
    {
      "day": 119,
      "sura": 10,
      "aya": 44
    },
    {
      "day": 120,
      "sura": 10,
      "aya": "55,56"
    },
    {
      "day": 121,
      "sura": 10,
      "aya": "57,58"
    },
    {
      "day": 122,
      "sura": 10,
      "aya": "62,63,64"
    },
    {
      "day": 123,
      "sura": 10,
      "aya": "71,72,84,85,86"
    },
    {
      "day": 124,
      "sura": 10,
      "aya": "99,100"
    },
    {
      "day": 125,
      "sura": 10,
      "aya": "104,105,106"
    },
    {
      "day": 126,
      "sura": 10,
      "aya": "108,109"
    },
    {
      "day": 127,
      "sura": 11,
      "aya": "2,3,4"
    },
    {
      "day": 128,
      "sura": 11,
      "aya": "6,7"
    },
    {
      "day": 129,
      "sura": 11,
      "aya": "9,10,11"
    },
    {
      "day": 130,
      "sura": 11,
      "aya": 23
    },
    {
      "day": 131,
      "sura": 11,
      "aya": "114,115"
    },
    {
      "day": 132,
      "sura": 11,
      "aya": "25,50,61,84,96,101"
    },
    {
      "day": 133,
      "sura": 11,
      "aya": 123
    },
    {
      "day": 134,
      "sura": 11,
      "aya": "50,51,52"
    },
    {
      "day": 135,
      "sura": 11,
      "aya": 61
    },
    {
      "day": 136,
      "sura": 11,
      "aya": "84,85"
    },
    {
      "day": 137,
      "sura": 13,
      "aya": 2
    },
    {
      "day": 138,
      "sura": 13,
      "aya": "3,4"
    },
    {
      "day": 139,
      "sura": 13,
      "aya": "8,9,10"
    },
    {
      "day": 140,
      "sura": 13,
      "aya": 11
    },
    {
      "day": 141,
      "sura": 13,
      "aya": "15,16"
    },
    {
      "day": 142,
      "sura": 13,
      "aya": "19,20,21,22,23,24"
    },
    {
      "day": 143,
      "sura": 13,
      "aya": 18
    },
    {
      "day": 144,
      "sura": 13,
      "aya": "28,29"
    },
    {
      "day": 145,
      "sura": 14,
      "aya": "10,11,12"
    },
    {
      "day": 146,
      "sura": 14,
      "aya": "24,25,26,27"
    },
    {
      "day": 147,
      "sura": 14,
      "aya": 31
    },
    {
      "day": 148,
      "sura": 14,
      "aya": "32,33,34"
    },
    {
      "day": 149,
      "sura": 14,
      "aya": "38,39,40,41"
    },
    {
      "day": 150,
      "sura": 14,
      "aya": "35,36,37"
    },
    {
      "day": 151,
      "sura": 15,
      "aya": "19,20,21,22,23,24,25"
    },
    {
      "day": 152,
      "sura": 15,
      "aya": "45,46,47,48,49,50"
    },
    {
      "day": 153,
      "sura": 16,
      "aya": "1,2"
    },
    {
      "day": 154,
      "sura": 16,
      "aya": "10,11,12,13"
    },
    {
      "day": 155,
      "sura": 16,
      "aya": "3,4,5,6,7,8"
    },
    {
      "day": 156,
      "sura": 16,
      "aya": "14,15,16,17,18"
    },
    {
      "day": 157,
      "sura": 16,
      "aya": "20,21,22,23"
    },
    {
      "day": 158,
      "sura": 16,
      "aya": "30,31,32"
    },
    {
      "day": 159,
      "sura": 16,
      "aya": "36,37"
    },
    {
      "day": 160,
      "sura": 16,
      "aya": "38,39,40"
    },
    {
      "day": 161,
      "sura": 16,
      "aya": "48,49,50,51"
    },
    {
      "day": 162,
      "sura": 16,
      "aya": "52,53,54,55"
    },
    {
      "day": 163,
      "sura": 16,
      "aya": "65,66,67"
    },
    {
      "day": 164,
      "sura": 16,
      "aya": "68,69,70"
    },
    {
      "day": 165,
      "sura": 16,
      "aya": "77,78,79"
    },
    {
      "day": 166,
      "sura": 16,
      "aya": "80,81"
    },
    {
      "day": 167,
      "sura": 16,
      "aya": "89,90"
    },
    {
      "day": 168,
      "sura": 16,
      "aya": 93
    },
    {
      "day": 169,
      "sura": 16,
      "aya": 97
    },
    {
      "day": 170,
      "sura": 16,
      "aya": "125,126,127,128"
    },
    {
      "day": 171,
      "sura": 17,
      "aya": "9,10"
    },
    {
      "day": 172,
      "sura": 17,
      "aya": "13,14,15"
    },
    {
      "day": 173,
      "sura": 17,
      "aya": "18,19,20,21,22"
    },
    {
      "day": 174,
      "sura": 17,
      "aya": "23,24,25"
    },
    {
      "day": 175,
      "sura": 17,
      "aya": "31,32,33"
    },
    {
      "day": 176,
      "sura": 17,
      "aya": "26,27,28,29,30"
    },
    {
      "day": 177,
      "sura": 17,
      "aya": "34,35,36"
    },
    {
      "day": 178,
      "sura": 17,
      "aya": "37,38,39"
    },
    {
      "day": 179,
      "sura": 17,
      "aya": "42,43,44"
    },
    {
      "day": 180,
      "sura": 17,
      "aya": "78,79,80,81"
    },
    {
      "day": 181,
      "sura": 17,
      "aya": "82,83,84"
    },
    {
      "day": 182,
      "sura": 17,
      "aya": "94,95,96"
    },
    {
      "day": 183,
      "sura": 18,
      "aya": "23,24"
    },
    {
      "day": 184,
      "sura": 18,
      "aya": 28
    },
    {
      "day": 185,
      "sura": 18,
      "aya": "46,47,48"
    },
    {
      "day": 186,
      "sura": 18,
      "aya": "103,104,105,106,107,108"
    },
    {
      "day": 187,
      "sura": 19,
      "aya": "2,3,4,5,6,7"
    },
    {
      "day": 188,
      "sura": 19,
      "aya": "51,52,53"
    },
    {
      "day": 189,
      "sura": 19,
      "aya": "16,17,18,19,20,21,22,23,24,25"
    },
    {
      "day": 190,
      "sura": 19,
      "aya": "26,27,28,29,30,31,32,33,34,35"
    },
    {
      "day": 191,
      "sura": 19,
      "aya": "41,42,43,44,45,46,47,48,49,50"
    },
    {
      "day": 192,
      "sura": 19,
      "aya": "54,55"
    },
    {
      "day": 193,
      "sura": 19,
      "aya": "56,57,58"
    },
    {
      "day": 194,
      "sura": 19,
      "aya": "59,60,61,62"
    },
    {
      "day": 195,
      "sura": 19,
      "aya": "63,64,65"
    },
    {
      "day": 196,
      "sura": 19,
      "aya": 96
    },
    {
      "day": 197,
      "sura": 20,
      "aya": "2,3,4,5,6,7,8"
    },
    {
      "day": 198,
      "sura": 20,
      "aya": "12,13,14,15,16"
    },
    {
      "day": 199,
      "sura": 20,
      "aya": "105,106,107,108"
    },
    {
      "day": 200,
      "sura": 20,
      "aya": "109,110,111,112"
    },
    {
      "day": 201,
      "sura": 20,
      "aya": "130,131,132"
    },
    {
      "day": 202,
      "sura": 21,
      "aya": "1,2,3"
    },
    {
      "day": 203,
      "sura": 21,
      "aya": "19,20,21,22,23"
    },
    {
      "day": 204,
      "sura": 21,
      "aya": "25,26,27,28,29"
    },
    {
      "day": 205,
      "sura": 21,
      "aya": "30,31,32,33"
    },
    {
      "day": 206,
      "sura": 21,
      "aya": "34,35"
    },
    {
      "day": 207,
      "sura": 21,
      "aya": "41,42,43"
    },
    {
      "day": 208,
      "sura": 21,
      "aya": "46,47"
    },
    {
      "day": 209,
      "sura": 21,
      "aya": "76,77,78,79,80,81,82,83,84,85,86,87,88,89,90,91,92,93,94"
    },
    {
      "day": 210,
      "sura": 21,
      "aya": "48,51,72,73,74,75"
    },
    {
      "day": 211,
      "sura": 21,
      "aya": "101,102,103,104"
    },
    {
      "day": 212,
      "sura": 21,
      "aya": "107,108"
    },
    {
      "day": 213,
      "sura": 22,
      "aya": "1,2"
    },
    {
      "day": 214,
      "sura": 22,
      "aya": "5,6,7"
    },
    {
      "day": 215,
      "sura": 22,
      "aya": 18
    },
    {
      "day": 216,
      "sura": 22,
      "aya": "34,35"
    },
    {
      "day": 217,
      "sura": 22,
      "aya": "40,41"
    },
    {
      "day": 218,
      "sura": 22,
      "aya": "63,64,65"
    },
    {
      "day": 219,
      "sura": 22,
      "aya": 66
    },
    {
      "day": 220,
      "sura": 22,
      "aya": "73,74"
    },
    {
      "day": 221,
      "sura": 22,
      "aya": "75,76,77,78"
    },
    {
      "day": 222,
      "sura": 23,
      "aya": "12,13,14,15,16"
    },
    {
      "day": 223,
      "sura": 23,
      "aya": "86,87,88,89,90"
    },
    {
      "day": 224,
      "sura": 23,
      "aya": "17,18,19,20,21,22"
    },
    {
      "day": 225,
      "sura": 23,
      "aya": "78,79,80,81,82,83,84,85"
    },
    {
      "day": 226,
      "sura": 23,
      "aya": "91,92"
    },
    {
      "day": 227,
      "sura": 23,
      "aya": "115,116,117,118"
    },
    {
      "day": 228,
      "sura": 24,
      "aya": "35,36,37"
    },
    {
      "day": 229,
      "sura": 24,
      "aya": "41,42"
    },
    {
      "day": 230,
      "sura": 25,
      "aya": "1,2,3"
    },
    {
      "day": 231,
      "sura": 24,
      "aya": "43,44,45,46"
    },
    {
      "day": 232,
      "sura": 25,
      "aya": "45,46,47,48,49,50"
    },
    {
      "day": 233,
      "sura": 25,
      "aya": "53,54"
    },
    {
      "day": 234,
      "sura": 25,
      "aya": "58,59,60"
    },
    {
      "day": 235,
      "sura": 25,
      "aya": "61,62,63,64,65,66,67,68"
    },
    {
      "day": 236,
      "sura": 25,
      "aya": "72,73,74,75,76"
    },
    {
      "day": 237,
      "sura": 27,
      "aya": "59,60"
    },
    {
      "day": 238,
      "sura": 26,
      "aya": "78,79,80,81,82,83,84,85,86,87,88,89"
    },
    {
      "day": 239,
      "sura": 26,
      "aya": "105,106,107,108,123,124,125,126,141,142,143,144,160,161,162,163,176,177,178,179"
    },
    {
      "day": 240,
      "sura": 27,
      "aya": "61,62"
    },
    {
      "day": 241,
      "sura": 27,
      "aya": "63,64"
    },
    {
      "day": 242,
      "sura": 27,
      "aya": 65
    },
    {
      "day": 243,
      "sura": 27,
      "aya": "73,74,75"
    },
    {
      "day": 244,
      "sura": 28,
      "aya": "60,61"
    },
    {
      "day": 245,
      "sura": 28,
      "aya": "83,84"
    },
    {
      "day": 246,
      "sura": 28,
      "aya": 88
    },
    {
      "day": 247,
      "sura": 29,
      "aya": "2,3,4,5,6,7"
    },
    {
      "day": 248,
      "sura": 29,
      "aya": "19,20,21,22"
    },
    {
      "day": 249,
      "sura": 29,
      "aya": "45,46"
    },
    {
      "day": 250,
      "sura": 29,
      "aya": "56,57,58,59"
    },
    {
      "day": 251,
      "sura": 29,
      "aya": 69
    },
    {
      "day": 252,
      "sura": 29,
      "aya": "60,61,62,63,64"
    },
    {
      "day": 253,
      "sura": 30,
      "aya": "7,8,9"
    },
    {
      "day": 254,
      "sura": 30,
      "aya": 11
    },
    {
      "day": 255,
      "sura": 30,
      "aya": "14,15,16,17"
    },
    {
      "day": 256,
      "sura": 30,
      "aya": "36,37,38"
    },
    {
      "day": 257,
      "sura": 30,
      "aya": "18,19,20,21,22"
    },
    {
      "day": 258,
      "sura": 30,
      "aya": "23,24,25,26,27"
    },
    {
      "day": 259,
      "sura": 30,
      "aya": 40
    },
    {
      "day": 260,
      "sura": 30,
      "aya": 41
    },
    {
      "day": 261,
      "sura": 30,
      "aya": "44,45"
    },
    {
      "day": 262,
      "sura": 31,
      "aya": "2,3,4,5"
    },
    {
      "day": 263,
      "sura": 31,
      "aya": "10,11"
    },
    {
      "day": 264,
      "sura": 31,
      "aya": 12
    },
    {
      "day": 265,
      "sura": 31,
      "aya": "13,14,15"
    },
    {
      "day": 266,
      "sura": 31,
      "aya": "16,17,18,19"
    },
    {
      "day": 267,
      "sura": 31,
      "aya": "26,27,28"
    },
    {
      "day": 268,
      "sura": 31,
      "aya": "29,30,31"
    },
    {
      "day": 269,
      "sura": 31,
      "aya": "33,34"
    },
    {
      "day": 270,
      "sura": 33,
      "aya": "70,71,72"
    },
    {
      "day": 271,
      "sura": 32,
      "aya": "4,5,6,7,8,9,10"
    },
    {
      "day": 272,
      "sura": 34,
      "aya": "1,2,3,4,5"
    },
    {
      "day": 273,
      "sura": 34,
      "aya": "28,29,30"
    },
    {
      "day": 274,
      "sura": 34,
      "aya": "37,38"
    },
    {
      "day": 275,
      "sura": 35,
      "aya": 10
    },
    {
      "day": 276,
      "sura": 39,
      "aya": 7
    },
    {
      "day": 277,
      "sura": 35,
      "aya": "11,12"
    },
    {
      "day": 278,
      "sura": 35,
      "aya": "27,28,29,30"
    },
    {
      "day": 279,
      "sura": 36,
      "aya": "33,34,35,36"
    },
    {
      "day": 280,
      "sura": 36,
      "aya": "78,79,80,81,82,83"
    },
    {
      "day": 281,
      "sura": 39,
      "aya": "4,5,6"
    },
    {
      "day": 282,
      "sura": 39,
      "aya": "10,11,12"
    },
    {
      "day": 283,
      "sura": 39,
      "aya": "21,22"
    },
    {
      "day": 284,
      "sura": 39,
      "aya": "36,37,38"
    },
    {
      "day": 285,
      "sura": 39,
      "aya": "53,54,55,56,57,58,59"
    },
    {
      "day": 286,
      "sura": 39,
      "aya": "67,68,69,70"
    },
    {
      "day": 287,
      "sura": 40,
      "aya": "2,3"
    },
    {
      "day": 288,
      "sura": 40,
      "aya": "7,8,9"
    },
    {
      "day": 289,
      "sura": 40,
      "aya": "14,15,16,17"
    },
    {
      "day": 290,
      "sura": 40,
      "aya": 40
    },
    {
      "day": 291,
      "sura": 40,
      "aya": "59,60,61,62,63,64,65"
    },
    {
      "day": 292,
      "sura": 40,
      "aya": "66,67,68"
    },
    {
      "day": 293,
      "sura": 41,
      "aya": "9,10,11,12"
    },
    {
      "day": 294,
      "sura": 41,
      "aya": "30,31,32,33"
    },
    {
      "day": 295,
      "sura": 41,
      "aya": "46,47"
    },
    {
      "day": 296,
      "sura": 41,
      "aya": "34,35,36,37,38"
    },
    {
      "day": 297,
      "sura": 41,
      "aya": "53,54"
    },
    {
      "day": 298,
      "sura": 42,
      "aya": "3,4,5"
    },
    {
      "day": 299,
      "sura": 42,
      "aya": "11,12"
    },
    {
      "day": 300,
      "sura": 42,
      "aya": 13
    },
    {
      "day": 301,
      "sura": 42,
      "aya": 15
    },
    {
      "day": 302,
      "sura": 42,
      "aya": "49,50,51"
    },
    {
      "day": 303,
      "sura": 42,
      "aya": "52,53"
    },
    {
      "day": 304,
      "sura": 43,
      "aya": 9
    },
    {
      "day": 305,
      "sura": 44,
      "aya": "38,39,40,41,42"
    },
    {
      "day": 306,
      "sura": 43,
      "aya": "10,11,12,13,14"
    },
    {
      "day": 307,
      "sura": 43,
      "aya": "80,81,82,83,84"
    },
    {
      "day": 308,
      "sura": 43,
      "aya": "85,86,87,88,89"
    },
    {
      "day": 309,
      "sura": 44,
      "aya": "7,8,9,10,11,12,13,14"
    },
    {
      "day": 310,
      "sura": 45,
      "aya": "2,3,4,5,6"
    },
    {
      "day": 311,
      "sura": 45,
      "aya": "12,13,14,15"
    },
    {
      "day": 312,
      "sura": 45,
      "aya": "34,35,36,37"
    },
    {
      "day": 313,
      "sura": 46,
      "aya": "2,3,4"
    },
    {
      "day": 314,
      "sura": 46,
      "aya": "13,14,15,16"
    },
    {
      "day": 315,
      "sura": 47,
      "aya": 2
    },
    {
      "day": 316,
      "sura": 49,
      "aya": 13
    },
    {
      "day": 317,
      "sura": 49,
      "aya": "11,12"
    },
    {
      "day": 318,
      "sura": 50,
      "aya": "6,7,8,9,10,11"
    },
    {
      "day": 319,
      "sura": 50,
      "aya": "15,16"
    },
    {
      "day": 320,
      "sura": 51,
      "aya": "20,21,22,23"
    },
    {
      "day": 321,
      "sura": 51,
      "aya": "47,48,49,50,51"
    },
    {
      "day": 322,
      "sura": 53,
      "aya": "39,40,41,42,43,44,45,46,47,48"
    },
    {
      "day": 323,
      "sura": 54,
      "aya": "49,50,51,52,53,54,55"
    },
    {
      "day": 324,
      "sura": 55,
      "aya": "1,2,3,4,5,6,7,8,9,10,11,12,13"
    },
    {
      "day": 325,
      "sura": 56,
      "aya": "58,59,60,61,62,63,64,65"
    },
    {
      "day": 326,
      "sura": 56,
      "aya": "68,69,70,71,72,73,74"
    },
    {
      "day": 327,
      "sura": 57,
      "aya": "1,2,3,4,5,6"
    },
    {
      "day": 328,
      "sura": 57,
      "aya": "9,10"
    },
    {
      "day": 329,
      "sura": 57,
      "aya": 18
    },
    {
      "day": 330,
      "sura": 57,
      "aya": 21
    },
    {
      "day": 331,
      "sura": 57,
      "aya": "22,23,24"
    },
    {
      "day": 332,
      "sura": 60,
      "aya": 5
    },
    {
      "day": 333,
      "sura": 60,
      "aya": "8,9"
    },
    {
      "day": 334,
      "sura": 59,
      "aya": "21,22,23,24"
    },
    {
      "day": 335,
      "sura": 61,
      "aya": "1,2,3"
    },
    {
      "day": 336,
      "sura": 61,
      "aya": "5,6,7,8"
    },
    {
      "day": 337,
      "sura": 61,
      "aya": 14
    },
    {
      "day": 338,
      "sura": 62,
      "aya": "1,2,3,4"
    },
    {
      "day": 339,
      "sura": 62,
      "aya": "9,10"
    },
    {
      "day": 340,
      "sura": 63,
      "aya": "9,10,11"
    },
    {
      "day": 341,
      "sura": 64,
      "aya": "1,2,3,4"
    },
    {
      "day": 342,
      "sura": 64,
      "aya": "11,12,13"
    },
    {
      "day": 343,
      "sura": 64,
      "aya": "15,16,17,18"
    },
    {
      "day": 344,
      "sura": 65,
      "aya": "2,3"
    },
    {
      "day": 345,
      "sura": 66,
      "aya": 8
    },
    {
      "day": 346,
      "sura": 66,
      "aya": "10,11,12"
    },
    {
      "day": 347,
      "sura": 67,
      "aya": "1,2,3,4"
    },
    {
      "day": 348,
      "sura": 67,
      "aya": "13,14,15"
    },
    {
      "day": 349,
      "sura": 67,
      "aya": "23,24,25,26"
    },
    {
      "day": 350,
      "sura": 67,
      "aya": "29,30"
    },
    {
      "day": 351,
      "sura": 71,
      "aya": "11,12,13,14,15,16,17,18"
    },
    {
      "day": 352,
      "sura": 72,
      "aya": "25,26,27,28"
    },
    {
      "day": 353,
      "sura": 75,
      "aya": "36,37,38,39,40"
    },
    {
      "day": 354,
      "sura": 76,
      "aya": "1,2,3"
    },
    {
      "day": 355,
      "sura": 78,
      "aya": "1,2,3,4,5,6,7,8,9,10,11,12,13,14,15,16,17"
    },
    {
      "day": 356,
      "sura": 80,
      "aya": "17,18,19,20,21,22,23"
    },
    {
      "day": 357,
      "sura": 80,
      "aya": "24,25,26,27,28,29,30,31,32"
    },
    {
      "day": 358,
      "sura": 87,
      "aya": "1,2,3,4,5"
    },
    {
      "day": 359,
      "sura": 88,
      "aya": "17,18,19,20"
    },
    {
      "day": 360,
      "sura": 90,
      "aya": "8,9,10"
    },
    {
      "day": 361,
      "sura": 96,
      "aya": "1,2,3,4,5,6,7,8"
    },
    {
      "day": 362,
      "sura": 98,
      "aya": "7,8"
    },
    {
      "day": 363,
      "sura": 99,
      "aya": "1,2,3,4,5,6,7,8"
    },
    {
      "day": 364,
      "sura": 103,
      "aya": "1,2,3"
    },
    {
      "day": 365,
      "sura": 112,
      "aya": "1,2,3,4"
    }
  ]
}